LICENSE
MANIFEST.in
README.rst
dev-requirements.txt
requirements.txt
setup.py
conf/config.py
conf/mts.toml
message_tagging_service/__init__.py
message_tagging_service/__main__.py
message_tagging_service/config.py
message_tagging_service/consumer.py
message_tagging_service/messaging.py
message_tagging_service/monitor.py
message_tagging_service/tagging_service.py
message_tagging_service/utils.py
message_tagging_service/web.py
message_tagging_service.egg-info/PKG-INFO
message_tagging_service.egg-info/SOURCES.txt
message_tagging_service.egg-info/dependency_links.txt
message_tagging_service.egg-info/requires.txt
message_tagging_service.egg-info/top_level.txt
rules/mts-rules.yaml
tests/__init__.py
tests/test_config.py
tests/test_consumer.py
tests/test_messaging.py
tests/test_service.py
tests/test_utils.py
tests/data/config.py
tests/data/mts-test-for-no-match.yaml
tests/data/mts-test-rules.yaml