Metadata-Version: 1.2
Name: message-tagging-service
Version: 0.8
Summary: Tag Koji build with correct tag which is triggered by message bus
Home-page: https://github.com/fedora-modularity/message-tagging-service
Maintainer: Factory 2 Team
Maintainer-email: message-tagging-service@fedoraproject.org
License: GPLv2+
Keywords: messaging,module,tag,koji
Platform: UNKNOWN
Classifier: License :: OSI Approved :: GNU Lesser General Public License v2 or later (LGPLv2+)
Classifier: Programming Language :: Python
Classifier: Programming Language :: Python :: 3.6
Classifier: Programming Language :: Python :: 3.7
